infographics/__init__.py
infographics/_constants.py
infographics/_utils.py
infographics/adaptors/ColorBase.py
infographics/adaptors/ColorHistogram.py
infographics/adaptors/ColorPercentVaryLightness.py
infographics/adaptors/SimpleLabel.py
infographics/adaptors/__init__.py
infographics/base/__init__.py
infographics/base/dorling_compress.py
infographics/base/ds.py
infographics/base/humanize.py
infographics/base/pandax.py
infographics/base/shapely.py
infographics/base/xy.py
infographics/core/Infographic.py
infographics/core/SVGPalette.py
infographics/core/SVGPalettePolygon.py
infographics/core/SVGPaletteSize.py
infographics/core/SVG_STYLES.py
infographics/core/__init__.py
infographics/data/AbstractData.py
infographics/data/GIGData.py
infographics/data/LKCensusData.py
infographics/data/LKCensusEthnicityData.py
infographics/data/LKCensusReligionData.py
infographics/data/LKElectionsData.py
infographics/data/LKGeoData.py
infographics/data/__init__.py
infographics/data/gig_utils.py
infographics/view/BarGraphBasic.py
infographics/view/DorlingView.py
infographics/view/FlagDorlingView.py
infographics/view/LegendView.py
infographics/view/PolygonView.py
infographics/view/__init__.py
infographics_nuuuwan-2.0.0.dist-info/LICENSE
infographics_nuuuwan-2.0.0.dist-info/METADATA
infographics_nuuuwan-2.0.0.dist-info/WHEEL
infographics_nuuuwan-2.0.0.dist-info/top_level.txt
infographics_nuuuwan-2.0.0.dist-info/RECORD
