Metadata-Version: 2.1
Name: infographics-nuuuwan
Version: 2.0.0
Summary: UNKNOWN
Home-page: https://github.com/nuuuwan/infographics
Author: Nuwan I. Senaratna
Author-email: nuuuwan@gmail.com
License: UNKNOWN
Project-URL: Bug Tracker, https://github.com/nuuuwan/infographics/issues
Platform: UNKNOWN
Classifier: Programming Language :: Python :: 3
Classifier: License :: OSI Approved :: MIT License
Classifier: Operating System :: OS Independent
Requires-Python: >=3.6
License-File: LICENSE
Requires-Dist: utils-nuuuwan
Requires-Dist: gig-nuuuwan
Requires-Dist: geo-nuuuwan
Requires-Dist: cairosvg
